gennav/__init__.py
gennav/controllers/__init__.py
gennav/controllers/base.py
gennav/controllers/PID/__init__.py
gennav/controllers/PID/common.py
gennav/controllers/PID/differential_pid.py
gennav/controllers/PID/omniwheel_PID.py
gennav/envs/__init__.py
gennav/envs/base.py
gennav/envs/common.py
gennav/envs/polygon_env.py
gennav/envs/scan_env.py
gennav/planners/__init__.py
gennav/planners/base.py
gennav/planners/graph_search/__init__.py
gennav/planners/graph_search/astar.py
gennav/planners/prm/__init__.py
gennav/planners/prm/prm.py
gennav/planners/rrt/__init__.py
gennav/planners/rrt/rrt.py
gennav/utils/__init__.py
gennav/utils/common.py
gennav/utils/geometry.py
gennav/utils/path_processing.py
gennav/utils/samplers.py
gennav/utils/visualisation.py
gennav-0.1.0.dist-info/LICENSE
gennav-0.1.0.dist-info/METADATA
gennav-0.1.0.dist-info/WHEEL
gennav-0.1.0.dist-info/top_level.txt
gennav-0.1.0.dist-info/RECORD
