Metadata-Version: 2.1
Name: gennav
Version: 0.1.0
Summary: Python Package for Robot Navigation Algorithms
Home-page: https://github.com/ERC-BPGC/gennav
Author: Electronics and Robotics Club (ERC) BITS Goa
Author-email: atharvs.twm@gmail.com
License: MIT
Project-URL: Bug Reports, https://github.com/ERC-BPGC/gennav/issues
Project-URL: Source, https://github.com/ERC-BPGC/gennav
Project-URL: About Us, http://erc-bpgc.github.io/
Keywords: path planning,robotics,motion planning,navigation,algorithms
Platform: UNKNOWN
Classifier: Development Status :: 3 - Alpha
Classifier: Intended Audience :: Developers
Classifier: Intended Audience :: Education
Classifier: Intended Audience :: Science/Research
Classifier: Natural Language :: English
Classifier: Topic :: Software Development
Classifier: Topic :: Scientific/Engineering :: Artificial Intelligence
Classifier: Topic :: Software Development :: Libraries :: Python Modules
Classifier: License :: OSI Approved :: MIT License
Classifier: Programming Language :: Python
Classifier: Programming Language :: Python :: 2.7
Classifier: Programming Language :: Python :: 3
Classifier: Programming Language :: Python :: 3.6
Requires-Python: >=2.7.0
Requires-Dist: descartes
Requires-Dist: matplotlib
Requires-Dist: numpy
Requires-Dist: shapely
